yonestools/__init__.py
yonestools/timedeal.py
yonestools-0.0.2.dist-info/METADATA
yonestools-0.0.2.dist-info/WHEEL
yonestools-0.0.2.dist-info/top_level.txt
yonestools-0.0.2.dist-info/RECORD
